mrvi/__init__.py
mrvi/_components.py
mrvi/_constants.py
mrvi/_model.py
mrvi/_module.py
mrvi/_types.py
mrvi/_utils.py
mrvi-1.0.1.dist-info/METADATA
mrvi-1.0.1.dist-info/WHEEL
mrvi-1.0.1.dist-info/licenses/LICENSE
mrvi-1.0.1.dist-info/RECORD
