Metadata-Version: 2.1
Name: mrvi
Version: 1.0.1
Summary: Multi-resolution Variational Inference
Project-URL: Documentation, https://mrvi.readthedocs.io/
Project-URL: Source, https://github.com/YosefLab/mrvi
Project-URL: Home-page, https://github.com/YosefLab/mrvi
Author: Justin Hong, Pierre Boyeau, Adam Gayoso, Can Ergen, Martin Kim
Maintainer-email: Justin Hong <justin.hong@columbia.edu>, Pierre Boyeau <pierreboyeau@berkeley.edu>, Martin Kim <martinkim@berkeley.edu>
License: BSD 3-Clause License
License-File: LICENSE
Requires-Python: >=3.9
Requires-Dist: scvi-tools[criticism]>=1.1.0
Requires-Dist: seaborn>=0.12.1
Requires-Dist: statsmodels>=0.13.0
Provides-Extra: dev
Requires-Dist: bump2version; extra == 'dev'
Requires-Dist: pre-commit; extra == 'dev'
Provides-Extra: doc
Requires-Dist: ipykernel; extra == 'doc'
Requires-Dist: myst-nb; extra == 'doc'
Requires-Dist: sphinx-autodoc-typehints; extra == 'doc'
Requires-Dist: sphinx-book-theme>=0.3.3; extra == 'doc'
Requires-Dist: sphinx-copybutton; extra == 'doc'
Requires-Dist: sphinx>=4; extra == 'doc'
Requires-Dist: sphinxcontrib-bibtex>=1.0.0; extra == 'doc'
Provides-Extra: test
Requires-Dist: pytest; extra == 'test'
Requires-Dist: pytest-cov; extra == 'test'
